bgs/__init__.py
bgs/gs.py
bgs-0.7.0.dist-info/LICENSE
bgs-0.7.0.dist-info/METADATA
bgs-0.7.0.dist-info/WHEEL
bgs-0.7.0.dist-info/top_level.txt
bgs-0.7.0.dist-info/RECORD
